OASYS1_LNLS_ShadowOui-0.2.1-py3.8-nspkg.pth
orangecontrib/shadow/lnls/data/test.dat
orangecontrib/shadow/lnls/menu/__init__.py
orangecontrib/shadow/lnls/menu/ow_shadow_LNLS_tools_menu.py
orangecontrib/shadow/lnls/widgets/gui/__init__.py
orangecontrib/shadow/lnls/widgets/gui/ow_lnls_shadow_widget.py
orangecontrib/shadow/lnls/widgets/gui/ow_lnls_shadow_widget_c.py
orangecontrib/shadow/lnls/widgets/utility/__init__.py
orangecontrib/shadow/lnls/widgets/utility/ow_beam_analysis.py
orangecontrib/shadow/lnls/widgets/utility/ow_caustic_widget.py
orangecontrib/shadow/lnls/widgets/utility/ow_flux_widget.py
orangecontrib/shadow/lnls/widgets/utility/ow_hybridinfo_widget.py
orangecontrib/shadow/lnls/widgets/utility/volume_slicer_mayavi.py
orangecontrib/shadow/lnls/widgets/utility/icons/beam_analysis_icon.png
orangecontrib/shadow/lnls/widgets/utility/icons/caustic_icon.png
orangecontrib/shadow/lnls/widgets/utility/icons/flux_icon.png
orangecontrib/shadow/lnls/widgets/utility/icons/utility.png
orangecontrib/shadow/lnls/widgets/utility/info/__init__.py
orangecontrib/shadow/lnls/widgets/utility/info/classes.py
orangecontrib/shadow/lnls/widgets/utility/info/funcs.py
OASYS1_LNLS_ShadowOui-0.2.1.dist-info/LICENSE
OASYS1_LNLS_ShadowOui-0.2.1.dist-info/METADATA
OASYS1_LNLS_ShadowOui-0.2.1.dist-info/WHEEL
OASYS1_LNLS_ShadowOui-0.2.1.dist-info/entry_points.txt
OASYS1_LNLS_ShadowOui-0.2.1.dist-info/namespace_packages.txt
OASYS1_LNLS_ShadowOui-0.2.1.dist-info/top_level.txt
OASYS1_LNLS_ShadowOui-0.2.1.dist-info/RECORD
