Metadata-Version: 2.1
Name: OASYS1-LNLS-ShadowOui
Version: 0.2.1
Summary: WIDGETS DEVELOPED FOR LNLS TO EXTEND SHADOWOUI FUNCTIONALITIES
Home-page: http://github.com/oasys-lnls-kit/OASYS1-LNLS-ShadowOui
Author: Sergio Augusto Lordano Luiz, Artur Clarindo Pinto, Bernd Christian Meyer
Author-email: artur.pinto@lnls.br
License: MIT
Download-URL: http://github.com/oasys-lnls-kit/OASYS1-LNLS-ShadowOui
Keywords: ray-tracing,simulator,oasys1
Platform: UNKNOWN
Classifier: Development Status :: 4 - Beta
Classifier: Environment :: X11 Applications :: Qt
Classifier: Environment :: Console
Classifier: Environment :: Plugins
Classifier: Programming Language :: Cython
Classifier: Programming Language :: Python
Classifier: Programming Language :: Python :: 3
Classifier: Intended Audience :: Science/Research
Requires-Dist: setuptools
Requires-Dist: optlnls (>=0.3.3)
